Metadata-Version: 2.1
Name: mgmail
Version: 1.1.0
Summary: Import document attachments from SMTP account
Home-page: https://github.com/papermerge/mg-mail
Author: Eugen Ciur
Author-email: eugen@papermerge.com
License: Apache 2.0 License
Keywords: SMTP,REST API,papermerge
Platform: UNKNOWN
Classifier: Programming Language :: Python :: 3
Classifier: License :: OSI Approved :: Apache Software License
Classifier: Operating System :: OS Independent
Requires-Python: >=3.6
